pymodaq_plugins_trinamic/__init__.py
pymodaq_plugins_trinamic/utils.py
pymodaq_plugins_trinamic/app/__init__.py
pymodaq_plugins_trinamic/daq_move_plugins/__init__.py
pymodaq_plugins_trinamic/daq_move_plugins/daq_move_Trinamic.py
pymodaq_plugins_trinamic/daq_viewer_plugins/__init__.py
pymodaq_plugins_trinamic/daq_viewer_plugins/plugins_0D/__init__.py
pymodaq_plugins_trinamic/daq_viewer_plugins/plugins_1D/__init__.py
pymodaq_plugins_trinamic/daq_viewer_plugins/plugins_2D/__init__.py
pymodaq_plugins_trinamic/daq_viewer_plugins/plugins_ND/__init__.py
pymodaq_plugins_trinamic/exporters/__init__.py
pymodaq_plugins_trinamic/extensions/__init__.py
pymodaq_plugins_trinamic/hardware/__init__.py
pymodaq_plugins_trinamic/hardware/trinamic.py
pymodaq_plugins_trinamic/models/__init__.py
pymodaq_plugins_trinamic/resources/__init__.py
pymodaq_plugins_trinamic/resources/config_template.toml
pymodaq_plugins_trinamic/resources/extended_publisher.py
pymodaq_plugins_trinamic/scanners/__init__.py
pymodaq_plugins_trinamic-0.0.4.dist-info/METADATA
pymodaq_plugins_trinamic-0.0.4.dist-info/WHEEL
pymodaq_plugins_trinamic-0.0.4.dist-info/entry_points.txt
pymodaq_plugins_trinamic-0.0.4.dist-info/licenses/LICENSE
pymodaq_plugins_trinamic-0.0.4.dist-info/RECORD
