Metadata-Version: 2.4
Name: pymodaq_plugins_trinamic
Version: 0.0.4
Summary: PyMoDAQ module for communication and readout from Trinamic stepper motor control units
Project-URL: Homepage, https://pymodaq.cnrs.fr
Project-URL: Documentation , https://pymodaq.cnrs.fr
Project-URL: Repository , https://github.com/ccabello99/pymodaq_plugins_trinamic
Author-email: Christian Cabello <christian.cabello@ip-paris.fr>
Maintainer-email: Christian Cabello <christian.cabello@ip-paris.fr>
License: The MIT License (MIT)
License-File: LICENSE
Classifier: Development Status :: 5 - Production/Stable
Classifier: Intended Audience :: Science/Research
Classifier: License :: OSI Approved :: MIT License
Classifier: Natural Language :: English
Classifier: Operating System :: OS Independent
Classifier: Programming Language :: Python :: 3.8
Classifier: Programming Language :: Python :: 3.9
Classifier: Programming Language :: Python :: 3.10
Classifier: Programming Language :: Python :: 3.11
Classifier: Topic :: Scientific/Engineering :: Human Machine Interfaces
Classifier: Topic :: Scientific/Engineering :: Visualization
Classifier: Topic :: Software Development :: Libraries :: Python Modules
Classifier: Topic :: Software Development :: User Interfaces
Requires-Python: >=3.9
Requires-Dist: pymodaq>=4.4.7
Requires-Dist: pytrinamic
